{
   "players": {},
   "match_info": {
      "par1": 4,
      "par2": 4,
      "par3": 5,
      "par4": 4,
      "par5": 3,
      "par6": 4,
      "par7": 3,
      "par8": 4,
      "par9": 5,
      "par10": 4,
      "par11": 4,
      "par12": 5,
      "par13": 4,
      "par14": 3,
      "par15": 4,
      "par16": 3,
      "par17": 4,
      "par18": 5,
      "match_code": "119148",
      "match_password": "password",
      "number_holes": "18",
      "match_name": "First Match",
      "start_time": "2023-02-27",
      "end_time": "2023-02-27",
      "home_team": "n/a",
      "away_team": "n/a",
      "match_type": "Singles",
      "gamemode": "Stroke Play",
      "id": 20
   },
   "lobby": [],
   "message": ""
}